{
  "project_info": {
    "project_number": "1014992286129",
    "project_id": "rachim-7d1d0",
    "storage_bucket": "rachim-7d1d0.appspot.com"
  },
  "client": [
    {
      "client_info": {
        "mobilesdk_app_id": "1:1014992286129:android:90b5795a8e65fac28a0d90",
        "android_client_info": {
          "package_name": "com.rachim"
        }
      },
      "oauth_client": [
        {
          "client_id": "1014992286129-7hhaiubi6fafmcrsn5400qapcbd9q6dv.apps.googleusercontent.com",
          "client_type": 3
        }
      ],
      "api_key": [
        {
          "current_key": "AIzaSyDpk2MNTMp6JFStXo4ZmfbvaGJ93EwO_dA"
        }
      ],
      "services": {
        "appinvite_service": {
          "other_platform_oauth_client": [
            {
              "client_id": "1014992286129-7hhaiubi6fafmcrsn5400qapcbd9q6dv.apps.googleusercontent.com",
              "client_type": 3
            }
          ]
        }
      }
    }
  ],
  "configuration_version": "1"
}